{"type": "blog", "blog_name": ".", "blog_url": "http://yanzoron.blog.ir/", "post_url_1": "http://yanzoron.blog.ir/1395/06/24/%D8%A7%D8%B2-%D8%A8%D8%B3-%DA%A9%D8%B1%DB%8C%D9%85-%D8%A8%D9%88%D8%AF-%DA%A9%D9%87-%D8%AF%D8%B1%D9%87%D9%85-%D8%AE%D8%B1%DB%8C%D8%AF-%D9%88-%D8%B1%D9%81%D8%AA-%D8%AF%D8%B1-%D8%A7%D8%B2%D8%AF%D8%AD%D8%A7%D9%85-%D8%8C-%D8%AD%D8%A7%D8%AC%D8%AA-%D9%85%D8%A7-%D9%86%DB%8C%D8%B2-%D8%AF%D8%A7%D8%AF%D9%87-%D8%B4%D8%AF", "post_title_1": "از بس کریم بود که درهم خرید و رفت / در ازدحام ، حاجت ما نیز داده شد...", "post_content_1": "بسم الله الرحمن الرحیم\n\nخاک حرم رسید ، دوا نیز داده شد\nآب حرم رسید، شفا نیز داده شد\n ***\nاصلا بهانه هاست که ما را می آورد\nبا دادن بهانه ، بها نیز داده شد\n ***\nهر جا اگر به خواسته ها لطف می شود\nدر این حرم نخواسته ها نیز داده شد\n ***\nاز بس کریم بود که درهم خرید و رفت\nدر ازدحام ، حاجت ما نیز داده شد\n*** \nاصلا به خواهش کم ما اکتفا نکرد\nما سنگ خواستیم ، طلا نیز داده شد\n ***\nمیخواستم به مشهد تو راهی ام کنند\nدیدم برات کرببلا نیز داده شد\n----------------------------------------\n\"علی اکبر لطیفیان\"", "post_url_2": "http://yanzoron.blog.ir/1395/06/21/%D8%A8%DB%8C-%D9%84%DB%8C%D8%A7%D9%82%D8%AA%DB%8C-%D8%AD%DA%A9%D8%A7%D9%85-%D8%B3%D8%B9%D9%88%D8%AF%DB%8C", "post_title_2": "بی لیاقتی حکام سعودی...", "post_content_2": "", "post_url_3": "http://yanzoron.blog.ir/1395/05/23/%D8%A7%D9%86%DB%8C%D8%B3-%D8%A7%D9%84%D9%86%D9%81%D9%88%D8%B3%D8%8C%D8%B3%D9%84%D8%B7%D8%A7%D9%86-%D8%B7%D9%88%D8%B3", "post_title_3": "انیس النفوس،سلطان طوس", "post_content_3": "\n", "post_url_4": "http://yanzoron.blog.ir/1395/05/13/%DB%8C%D8%A7-%D9%81%D8%A7%D8%B7%D9%85%DB%80-%D8%A7%D8%B4%D9%81%D8%B9%DB%8C%D9%84%DB%8C-%D9%81%DB%8C-%D8%A7%D9%84%D8%AC%D9%86%DB%80", "post_title_4": "\"یا فاطمۀ اشفعیلی فی الجنۀ\"", "post_content_4": "همسایه سایه ات به سرم مستدام باد\n\nلطفت همیشه زخم مرا التیام داد\n\nوقتی انیس لحظه ی تنهایی ام توئی\n\nتنها دلیل اینکه من اینجایی ام توئی\n\nهر شب دلم قدم به قدم میکشد مرا\n\nبی اختیار سمت حرم میکشد مرا\n\nبا شور شهر فاصله دارم کنار تو\n\nاحساس وصل میکند آدم کنار تو\n\nحالی نگفتنی  به دلم دست میدهد\n\nدر هر نماز مسجد اعظم کنار تو\n\nبانو! تمام کشور ما خاک زیر پات\n\nمردان شهر نوکرو  زن ها کنیز ه ات\n\nاعجاز این ضریح که همواره بی حد است\n\nچیزی شبیه پنجره فولاد مشهد است\n\nقم سالهاست با نفسش زنده مانده است\n\nباور کنید پیش مسیحا نشسته ایم\n\nبوی مدینه می وزد از شهر ما،بیا\n\nما در جوار حضرت زهرا نشسته ایم\n\nاز ما به جز بدی که ندیدی ببخشمان\n\nاز دست ما چه ها که کشیدی ببخشمان\n\n                             من هم دلیل حسرت افلاک می شوم\n\n                            روزی که زیر پای شما خاک می شوم\n\n         ", "post_url_5": "http://yanzoron.blog.ir/1395/05/06/%D8%A5%D9%86%D9%91%D9%8E%20%D9%84%D9%90%D9%82%D9%8E%D8%AA%D9%92%D9%84%D9%90%20%D8%A7%D9%84%D9%92%D8%AD%D9%8F%D8%B3%D9%8E%D9%8A%D9%92%D9%86%D9%90%20%D8%AD%D9%8E%D8%B1%D9%8E%D8%A7%D8%B1%D9%8E%D8%A9%D9%8C%20%D9%81%D9%90%D9%8A%20%D9%82%D9%8F%D9%84%D9%8F%D9%88%D8%A8%D9%90%20%D8%A7%D9%84%D9%92%D9%85%D9%8F%D8%A4%D9%92%D9%85%D9%90%D9%86%D9%90%D9%8A%D9%86%D9%8E", "post_title_5": "إنَّ لِقَتْلِ الْحُسَیْنِ حَرَارَةٌ فِی قُلُوبِ الْمُؤْمِنِینَ", "post_content_5": "بسم الله الرحمن الرحیم\n\n\n\n\n\n\n\n\n\t\t\t\t\t\tمتاسفانه مرورگر شما، قابیلت پخش فایل های صوتی تصویری را در قالب HTML5 دارا نمی باشد.\n\t\t\t\t\t\tتوصیه ما به شما استفاده از مروگرهای رایج و بروزرسانی آن به آخرین نسخه می باشد\n\t\t\t\t\t\tبا این حال ممکن است مرورگرتان توسط پلاگین خود قابلیت پخش این فایل را برای تان فراهم آورد.\n\n\n\n\t\t\t\t\t\t\t\n\t\t\t\t\t\t\tparam name=\"AutoStart\" value=\"False\"\n\t\t\t\t\t\t\t\n\n\n\n\n\n\n\n\n\n//دریافت//کلیپی از سخنرانی استاد پناهیان پیرو موضوع\"زیارت امام حسین(ع)\"\n\nقال رسول الله (ع) :« إنَّ لِقَتْلِ الْحُسَیْنِ حَرَارَةٌ فِی قُلُوبِ الْمُؤْمِنِینَ لَنْ تَبْرُدَ أَبَداً »\n", "post_full_content_5": "\nإنَّ لِقَتْلِ الْحُسَیْنِ حَرَارَةٌ فِی قُلُوبِ الْمُؤْمِنِینَ\n\n\n\nبسم الله الرحمن الرحیم\n\n\n\n\n\n\n\n\n\t\t\t\t\t\tمتاسفانه مرورگر شما، قابیلت پخش فایل های صوتی تصویری را در قالب HTML5 دارا نمی باشد.\n\t\t\t\t\t\tتوصیه ما به شما استفاده از مروگرهای رایج و بروزرسانی آن به آخرین نسخه می باشد\n\t\t\t\t\t\tبا این حال ممکن است مرورگرتان توسط پلاگین خود قابلیت پخش این فایل را برای تان فراهم آورد.\n\n\n\n\t\t\t\t\t\t\t\n\t\t\t\t\t\t\tparam name=\"AutoStart\" value=\"False\"\n\t\t\t\t\t\t\t\n\n\n\n\n\n\n\n\n\n//دریافت//کلیپی از سخنرانی استاد پناهیان پیرو موضوع\"زیارت امام حسین(ع)\"\n\nقال رسول الله (ع) :« إنَّ لِقَتْلِ الْحُسَیْنِ حَرَارَةٌ فِی قُلُوبِ الْمُؤْمِنِینَ لَنْ تَبْرُدَ أَبَداً »\n\n\n", "post_full_content_4": "\n\"یا فاطمۀ اشفعیلی فی الجنۀ\"\n\n\n\nهمسایه سایه ات به سرم مستدام باد\n\nلطفت همیشه زخم مرا التیام داد\n\nوقتی انیس لحظه ی تنهایی ام توئی\n\nتنها دلیل اینکه من اینجایی ام توئی\n\nهر شب دلم قدم به قدم میکشد مرا\n\nبی اختیار سمت حرم میکشد مرا\n\nبا شور شهر فاصله دارم کنار تو\n\nاحساس وصل میکند آدم کنار تو\n\nحالی نگفتنی  به دلم دست میدهد\n\nدر هر نماز مسجد اعظم کنار تو\n\nبانو! تمام کشور ما خاک زیر پات\n\nمردان شهر نوکرو  زن ها کنیز ه ات\n\nاعجاز این ضریح که همواره بی حد است\n\nچیزی شبیه پنجره فولاد مشهد است\n\nقم سالهاست با نفسش زنده مانده است\n\nباور کنید پیش مسیحا نشسته ایم\n\nبوی مدینه می وزد از شهر ما،بیا\n\nما در جوار حضرت زهرا نشسته ایم\n\nاز ما به جز بدی که ندیدی ببخشمان\n\nاز دست ما چه ها که کشیدی ببخشمان\n\n                             من هم دلیل حسرت افلاک می شوم\n\n                            روزی که زیر پای شما خاک می شوم\n\n         \n\n", "post_full_content_3": "\nانیس النفوس،سلطان طوس\n\n\n\n\n\n\n", "post_full_content_2": "\nبی لیاقتی حکام سعودی...\n\n\n\n\n\n", "post_full_content_1": "\nاز بس کریم بود که درهم خرید و رفت / در ازدحام ، حاجت ما نیز داده شد...\n\n\n\nبسم الله الرحمن الرحیم\n\nخاک حرم رسید ، دوا نیز داده شد\nآب حرم رسید، شفا نیز داده شد\n ***\nاصلا بهانه هاست که ما را می آورد\nبا دادن بهانه ، بها نیز داده شد\n ***\nهر جا اگر به خواسته ها لطف می شود\nدر این حرم نخواسته ها نیز داده شد\n ***\nاز بس کریم بود که درهم خرید و رفت\nدر ازدحام ، حاجت ما نیز داده شد\n*** \nاصلا به خواهش کم ما اکتفا نکرد\nما سنگ خواستیم ، طلا نیز داده شد\n ***\nمیخواستم به مشهد تو راهی ام کنند\nدیدم برات کرببلا نیز داده شد\n----------------------------------------\n\"علی اکبر لطیفیان\"\n\n"}