{"type": "blog", "blog_name": "مرجع کانتر در ایران | IRANCSBAX.BLOG.IR", "blog_url": "http://irancsbax.blog.ir/", "post_url_1": "http://irancsbax.blog.ir/1396/04/09/ERFAN-ADMIN", "post_title_1": "ERFAN ADMIN", "post_content_1": "ERFAN ADMIN", "post_url_2": "http://irancsbax.blog.ir/1396/04/08/erfan", "post_title_2": "erfan", "post_content_2": "erfan***", "post_url_3": "http://irancsbax.blog.ir/1396/04/06/5-160-138-38-20000-%D9%81%D8%A7%D9%86-%D8%B3%D8%B1-%D9%88%D8%B1", "post_title_3": "5.160.138.38:20000                  فان سر ور", "post_content_3": "", "post_url_4": "http://irancsbax.blog.ir/1396/04/04/ZP", "post_title_4": "ZP :  185.140.12.138:25000", "post_content_4": "", "post_url_5": "http://irancsbax.blog.ir/1396/03/15/%D8%A7%D8%B3%DA%A9%DB%8C%D9%86-SG552-%DA%A9%D8%A7%D9%86%D8%AA%D8%B1-%D8%B3%D9%88%D8%B1%D8%B3", "post_title_5": "اسکین SG552 | کانتر سورس", "post_content_5": "\n\n\n\n\n\nاسکین بسیار زیبا برای SG552 .....\nدریافتعنوان: SG552حجم: 9.8 مگابایتکاملا سالم\n\n\n\n\nبرگرفته شده از ircss.blog.ir "}